pyhuff/__init__.py
pyhuff/core/__init__.py
pyhuff/core/utils.py
pyhuff-1.1.data/scripts/pyhuff
pyhuff-1.1.dist-info/METADATA
pyhuff-1.1.dist-info/WHEEL
pyhuff-1.1.dist-info/top_level.txt
pyhuff-1.1.dist-info/RECORD
