Metadata-Version: 2.1
Name: pyhuff
Version: 1.1
Summary: This is a huffman code compressor
Home-page: https://github.com/projeto-de-algoritmos-2019-2/project-3-huffman-code-cli
Author: Victor Moura, Durval Carvalho
Author-email: victor_cmoura@hotmail.com, durvalcsouza@outlook.com
License: GPL-3.0
Platform: UNKNOWN
